<annotation>
	<folder></folder>
	<filename>frame_006234_png.rf.7396f0a8efb6a6f5c5383533bc38aeab.jpg</filename>
	<path>frame_006234_png.rf.7396f0a8efb6a6f5c5383533bc38aeab.jpg</path>
	<source>
		<database>roboflow.com</database>
	</source>
	<size>
		<width>640</width>
		<height>640</height>
		<depth>3</depth>
	</size>
	<segmented>0</segmented>
	<object>
		<name>pillar</name>
		<pose>Unspecified</pose>
		<truncated>0</truncated>
		<difficult>0</difficult>
		<occluded>0</occluded>
		<bndbox>
			<xmin>61</xmin>
			<xmax>82</xmax>
			<ymin>248</ymin>
			<ymax>469</ymax>
		</bndbox>
	</object>
	<object>
		<name>window</name>
		<pose>Unspecified</pose>
		<truncated>0</truncated>
		<difficult>0</difficult>
		<occluded>0</occluded>
		<bndbox>
			<xmin>1</xmin>
			<xmax>640</xmax>
			<ymin>1</ymin>
			<ymax>321</ymax>
		</bndbox>
	</object>
	<object>
		<name>tiled floor</name>
		<pose>Unspecified</pose>
		<truncated>0</truncated>
		<difficult>0</difficult>
		<occluded>0</occluded>
		<bndbox>
			<xmin>1</xmin>
			<xmax>639</xmax>
			<ymin>381</ymin>
			<ymax>638</ymax>
		</bndbox>
	</object>
	<object>
		<name>light bulb</name>
		<pose>Unspecified</pose>
		<truncated>0</truncated>
		<difficult>0</difficult>
		<occluded>0</occluded>
		<bndbox>
			<xmin>284</xmin>
			<xmax>291</xmax>
			<ymin>326</ymin>
			<ymax>340</ymax>
		</bndbox>
	</object>
</annotation>
