<annotation>
	<folder></folder>
	<filename>frame_002256_png.rf.89ef85a64b4d0297083cf98168580f58.jpg</filename>
	<path>frame_002256_png.rf.89ef85a64b4d0297083cf98168580f58.jpg</path>
	<source>
		<database>roboflow.com</database>
	</source>
	<size>
		<width>640</width>
		<height>640</height>
		<depth>3</depth>
	</size>
	<segmented>0</segmented>
	<object>
		<name>door</name>
		<pose>Unspecified</pose>
		<truncated>0</truncated>
		<difficult>0</difficult>
		<occluded>0</occluded>
		<bndbox>
			<xmin>316</xmin>
			<xmax>640</xmax>
			<ymin>1</ymin>
			<ymax>362</ymax>
		</bndbox>
		<polygon>
			<x1>590</x1>
			<y1>0</y1>
			<x2>315</x2>
			<y2>54.666667</y2>
			<x3>316</x3>
			<y3>121.333333</y3>
			<x4>325</x4>
			<y4>128</y4>
			<x5>331</x5>
			<y5>141.333333</y5>
			<x6>331</x6>
			<y6>157.333333</y6>
			<x7>338</x7>
			<y7>174.666667</y7>
			<x8>338</x8>
			<y8>217.333333</y8>
			<x9>341</x9>
			<y9>228</y9>
			<x10>349</x10>
			<y10>226.666667</y10>
			<x11>359</x11>
			<y11>234.666667</y11>
			<x12>351</x12>
			<y12>256</y12>
			<x13>347</x13>
			<y13>292</y13>
			<x14>363</x14>
			<y14>297.333333</y14>
			<x15>369</x15>
			<y15>297.333333</y15>
			<x16>371</x16>
			<y16>292</y16>
			<x17>392</x17>
			<y17>305.333333</y17>
			<x18>394</x18>
			<y18>348</y18>
			<x19>386</x19>
			<y19>357.333333</y19>
			<x20>393</x20>
			<y20>361.333333</y20>
			<x21>420</x21>
			<y21>354.666667</y21>
			<x22>548</x22>
			<y22>357.333333</y22>
			<x23>551</x23>
			<y23>350.666667</y23>
			<x24>565</x24>
			<y24>346.666667</y24>
			<x25>616</x25>
			<y25>350.666667</y25>
			<x26>621</x26>
			<y26>357.333333</y26>
			<x27>630</x27>
			<y27>358.666667</y27>
			<x28>636</x28>
			<y28>356</y28>
			<x29>639</x29>
			<y29>341.333333</y29>
			<x30>639</x30>
			<y30>0</y30>
			<x31>633.555556</x31>
			<y31>0</y31>
			<x32>590</x32>
			<y32>0</y32>
		</polygon>
	</object>
	<object>
		<name>light bulb</name>
		<pose>Unspecified</pose>
		<truncated>0</truncated>
		<difficult>0</difficult>
		<occluded>0</occluded>
		<bndbox>
			<xmin>413</xmin>
			<xmax>438</xmax>
			<ymin>90</ymin>
			<ymax>129</ymax>
		</bndbox>
		<polygon>
			<x1>414</x1>
			<y1>89.333333</y1>
			<x2>412</x2>
			<y2>97.333333</y2>
			<x3>421</x3>
			<y3>113.333333</y3>
			<x4>437</x4>
			<y4>128</y4>
			<x5>437</x5>
			<y5>118.666667</y5>
			<x6>418</x6>
			<y6>89.333333</y6>
			<x7>414</x7>
			<y7>89.333333</y7>
		</polygon>
	</object>
	<object>
		<name>light bulb</name>
		<pose>Unspecified</pose>
		<truncated>0</truncated>
		<difficult>0</difficult>
		<occluded>0</occluded>
		<bndbox>
			<xmin>438</xmin>
			<xmax>450</xmax>
			<ymin>129</ymin>
			<ymax>144</ymax>
		</bndbox>
		<polygon>
			<x1>449</x1>
			<y1>142.666667</y1>
			<x2>448</x2>
			<y2>133.333333</y2>
			<x3>437</x3>
			<y3>128</y3>
			<x4>443</x4>
			<y4>142.666667</y4>
			<x5>449</x5>
			<y5>142.666667</y5>
		</polygon>
	</object>
	<object>
		<name>light bulb</name>
		<pose>Unspecified</pose>
		<truncated>0</truncated>
		<difficult>0</difficult>
		<occluded>0</occluded>
		<bndbox>
			<xmin>413</xmin>
			<xmax>438</xmax>
			<ymin>90</ymin>
			<ymax>128</ymax>
		</bndbox>
		<polygon>
			<x1>437</x1>
			<y1>126.666667</y1>
			<x2>435</x2>
			<y2>114.666667</y2>
			<x3>418</x3>
			<y3>89.333333</y3>
			<x4>414</x4>
			<y4>89.333333</y4>
			<x5>412</x5>
			<y5>96</y5>
			<x6>423</x6>
			<y6>116</y6>
			<x7>430</x7>
			<y7>125.333333</y7>
			<x8>437</x8>
			<y8>126.666667</y8>
		</polygon>
	</object>
	<object>
		<name>light bulb</name>
		<pose>Unspecified</pose>
		<truncated>0</truncated>
		<difficult>0</difficult>
		<occluded>0</occluded>
		<bndbox>
			<xmin>440</xmin>
			<xmax>450</xmax>
			<ymin>130</ymin>
			<ymax>145</ymax>
		</bndbox>
		<polygon>
			<x1>444</x1>
			<y1>129.333333</y1>
			<x2>440</x2>
			<y2>129.333333</y2>
			<x3>439</x3>
			<y3>138.666667</y3>
			<x4>448</x4>
			<y4>144</y4>
			<x5>449</x5>
			<y5>136</y5>
			<x6>444</x6>
			<y6>129.333333</y6>
		</polygon>
	</object>
	<object>
		<name>pillar</name>
		<pose>Unspecified</pose>
		<truncated>0</truncated>
		<difficult>0</difficult>
		<occluded>0</occluded>
		<bndbox>
			<xmin>1</xmin>
			<xmax>55</xmax>
			<ymin>1</ymin>
			<ymax>404</ymax>
		</bndbox>
		<polygon>
			<x1>0</x1>
			<y1>0</y1>
			<x2>0</x2>
			<y2>390.666667</y2>
			<x3>13</x3>
			<y3>392</y3>
			<x4>18</x4>
			<y4>402.666667</y4>
			<x5>41</x5>
			<y5>373.333333</y5>
			<x6>54</x6>
			<y6>321.333333</y6>
			<x7>49</x7>
			<y7>236</y7>
			<x8>40</x8>
			<y8>205.333333</y8>
			<x9>27</x9>
			<y9>182.666667</y9>
			<x10>34</x10>
			<y10>168</y10>
			<x11>31</x11>
			<y11>133.333333</y11>
			<x12>40</x12>
			<y12>130.666667</y12>
			<x13>49</x13>
			<y13>128</y13>
			<x14>50</x14>
			<y14>0</y14>
			<x15>45</x15>
			<y15>0</y15>
			<x16>0</x16>
			<y16>0</y16>
		</polygon>
	</object>
	<object>
		<name>light bulb</name>
		<pose>Unspecified</pose>
		<truncated>0</truncated>
		<difficult>0</difficult>
		<occluded>0</occluded>
		<bndbox>
			<xmin>52</xmin>
			<xmax>58</xmax>
			<ymin>53</ymin>
			<ymax>62</ymax>
		</bndbox>
		<polygon>
			<x1>53</x1>
			<y1>52</y1>
			<x2>51</x2>
			<y2>61.333333</y2>
			<x3>57</x3>
			<y3>60</y3>
			<x4>56</x4>
			<y4>52</y4>
			<x5>53</x5>
			<y5>52</y5>
		</polygon>
	</object>
	<object>
		<name>person</name>
		<pose>Unspecified</pose>
		<truncated>0</truncated>
		<difficult>0</difficult>
		<occluded>0</occluded>
		<bndbox>
			<xmin>137</xmin>
			<xmax>178</xmax>
			<ymin>124</ymin>
			<ymax>378</ymax>
		</bndbox>
		<polygon>
			<x1>139</x1>
			<y1>258.666667</y1>
			<x2>145</x2>
			<y2>272</y2>
			<x3>146</x3>
			<y3>289.333333</y3>
			<x4>143</x4>
			<y4>332</y4>
			<x5>145</x5>
			<y5>377.333333</y5>
			<x6>164</x6>
			<y6>374.666667</y6>
			<x7>158</x7>
			<y7>345.333333</y7>
			<x8>163</x8>
			<y8>309.333333</y8>
			<x9>169</x9>
			<y9>296</y9>
			<x10>171</x10>
			<y10>265.333333</y10>
			<x11>154</x11>
			<y11>201.333333</y11>
			<x12>158</x12>
			<y12>192</y12>
			<x13>160</x13>
			<y13>160</y13>
			<x14>177</x14>
			<y14>141.333333</y14>
			<x15>174</x15>
			<y15>128</y15>
			<x16>168</x16>
			<y16>122.666667</y16>
			<x17>160</x17>
			<y17>122.666667</y17>
			<x18>136</x18>
			<y18>172</y18>
			<x19>144</x19>
			<y19>182.666667</y19>
			<x20>137</x20>
			<y20>208</y20>
			<x21>139</x21>
			<y21>258.666667</y21>
		</polygon>
	</object>
	<object>
		<name>person</name>
		<pose>Unspecified</pose>
		<truncated>0</truncated>
		<difficult>0</difficult>
		<occluded>0</occluded>
		<bndbox>
			<xmin>289</xmin>
			<xmax>344</xmax>
			<ymin>136</ymin>
			<ymax>377</ymax>
		</bndbox>
		<polygon>
			<x1>309</x1>
			<y1>168</y1>
			<x2>309</x2>
			<y2>228</y2>
			<x3>296</x3>
			<y3>240</y3>
			<x4>292</x4>
			<y4>256</y4>
			<x5>298</x5>
			<y5>258.666667</y5>
			<x6>306</x6>
			<y6>244</y6>
			<x7>310</x7>
			<y7>244</y7>
			<x8>315</x8>
			<y8>302.666667</y8>
			<x9>324</x9>
			<y9>338.666667</y9>
			<x10>323</x10>
			<y10>357.333333</y10>
			<x11>304</x11>
			<y11>373.333333</y11>
			<x12>331</x12>
			<y12>376</y12>
			<x13>343</x13>
			<y13>370.666667</y13>
			<x14>332</x14>
			<y14>289.333333</y14>
			<x15>338</x15>
			<y15>256</y15>
			<x16>334</x16>
			<y16>217.333333</y16>
			<x17>336</x17>
			<y17>174.666667</y17>
			<x18>322</x18>
			<y18>146.666667</y18>
			<x19>311</x19>
			<y19>150.666667</y19>
			<x20>301</x20>
			<y20>134.666667</y20>
			<x21>295</x21>
			<y21>134.666667</y21>
			<x22>289</x22>
			<y22>141.333333</y22>
			<x23>288</x23>
			<y23>154.666667</y23>
			<x24>298</x24>
			<y24>169.333333</y24>
			<x25>309</x25>
			<y25>168</y25>
		</polygon>
	</object>
	<object>
		<name>person</name>
		<pose>Unspecified</pose>
		<truncated>0</truncated>
		<difficult>0</difficult>
		<occluded>0</occluded>
		<bndbox>
			<xmin>247</xmin>
			<xmax>303</xmax>
			<ymin>164</ymin>
			<ymax>260</ymax>
		</bndbox>
		<polygon>
			<x1>248</x1>
			<y1>209.333333</y1>
			<x2>246</x2>
			<y2>233.333333</y2>
			<x3>255</x3>
			<y3>238.666667</y3>
			<x4>254</x4>
			<y4>258.666667</y4>
			<x5>279</x5>
			<y5>257.333333</y5>
			<x6>281</x6>
			<y6>225.333333</y6>
			<x7>285</x7>
			<y7>216</y7>
			<x8>294</x8>
			<y8>233.333333</y8>
			<x9>302</x9>
			<y9>228</y9>
			<x10>283</x10>
			<y10>193.333333</y10>
			<x11>285</x11>
			<y11>170.666667</y11>
			<x12>279</x12>
			<y12>162.666667</y12>
			<x13>275</x13>
			<y13>162.666667</y13>
			<x14>270</x14>
			<y14>172</y14>
			<x15>269</x15>
			<y15>186.666667</y15>
			<x16>255</x16>
			<y16>193.333333</y16>
			<x17>248</x17>
			<y17>209.333333</y17>
		</polygon>
	</object>
	<object>
		<name>person</name>
		<pose>Unspecified</pose>
		<truncated>0</truncated>
		<difficult>0</difficult>
		<occluded>0</occluded>
		<bndbox>
			<xmin>156</xmin>
			<xmax>244</xmax>
			<ymin>109</ymin>
			<ymax>386</ymax>
		</bndbox>
		<polygon>
			<x1>161</x1>
			<y1>158.666667</y1>
			<x2>155</x2>
			<y2>205.333333</y2>
			<x3>166</x3>
			<y3>237.333333</y3>
			<x4>167</x4>
			<y4>252</y4>
			<x5>172</x5>
			<y5>258.666667</y5>
			<x6>168</x6>
			<y6>381.333333</y6>
			<x7>190</x7>
			<y7>380</y7>
			<x8>181</x8>
			<y8>360</y8>
			<x9>181</x9>
			<y9>336</y9>
			<x10>191</x10>
			<y10>280</y10>
			<x11>197</x11>
			<y11>276</y11>
			<x12>212</x12>
			<y12>309.333333</y12>
			<x13>212</x13>
			<y13>374.666667</y13>
			<x14>208</x14>
			<y14>381.333333</y14>
			<x15>213</x15>
			<y15>385.333333</y15>
			<x16>236</x16>
			<y16>384</y16>
			<x17>236</x17>
			<y17>378.666667</y17>
			<x18>227</x18>
			<y18>370.666667</y18>
			<x19>227</x19>
			<y19>309.333333</y19>
			<x20>225</x20>
			<y20>292</y20>
			<x21>220</x21>
			<y21>288</y21>
			<x22>228</x22>
			<y22>281.333333</y22>
			<x23>230</x23>
			<y23>288</y23>
			<x24>241</x24>
			<y24>292</y24>
			<x25>243</x25>
			<y25>265.333333</y25>
			<x26>238</x26>
			<y26>262.666667</y26>
			<x27>233</x27>
			<y27>245.333333</y27>
			<x28>216</x28>
			<y28>148</y28>
			<x29>201</x29>
			<y29>137.333333</y29>
			<x30>204</x30>
			<y30>128</y30>
			<x31>202</x31>
			<y31>114.666667</y31>
			<x32>195</x32>
			<y32>108</y32>
			<x33>193</x33>
			<y33>108</y33>
			<x34>186</x34>
			<y34>113.333333</y34>
			<x35>186</x35>
			<y35>130.666667</y35>
			<x36>182</x36>
			<y36>137.333333</y36>
			<x37>161</x37>
			<y37>158.666667</y37>
		</polygon>
	</object>
	<object>
		<name>table</name>
		<pose>Unspecified</pose>
		<truncated>0</truncated>
		<difficult>0</difficult>
		<occluded>0</occluded>
		<bndbox>
			<xmin>25</xmin>
			<xmax>152</xmax>
			<ymin>166</ymin>
			<ymax>421</ymax>
		</bndbox>
		<polygon>
			<x1>56</x1>
			<y1>276</y1>
			<x2>56</x2>
			<y2>324</y2>
			<x3>48</x3>
			<y3>362.666667</y3>
			<x4>40</x4>
			<y4>380</y4>
			<x5>25</x5>
			<y5>397.333333</y5>
			<x6>24</x6>
			<y6>405.333333</y6>
			<x7>46</x7>
			<y7>405.333333</y7>
			<x8>54</x8>
			<y8>420</y8>
			<x9>111</x9>
			<y9>405.333333</y9>
			<x10>138</x10>
			<y10>404</y10>
			<x11>141</x11>
			<y11>410.666667</y11>
			<x12>151</x12>
			<y12>409.333333</y12>
			<x13>151</x13>
			<y13>396</y13>
			<x14>135</x14>
			<y14>374.666667</y14>
			<x15>124</x15>
			<y15>348</y15>
			<x16>117</x16>
			<y16>305.333333</y16>
			<x17>118</x17>
			<y17>253.333333</y17>
			<x18>127</x18>
			<y18>216</y18>
			<x19>142</x19>
			<y19>182.666667</y19>
			<x20>126</x20>
			<y20>172</y20>
			<x21>77</x21>
			<y21>165.333333</y21>
			<x22>71.333333</x22>
			<y22>165.333333</y22>
			<x23>36</x23>
			<y23>169.333333</y23>
			<x24>28</x24>
			<y24>178.666667</y24>
			<x25>49</x25>
			<y25>225.333333</y25>
			<x26>56</x26>
			<y26>276</y26>
		</polygon>
	</object>
	<object>
		<name>desk</name>
		<pose>Unspecified</pose>
		<truncated>0</truncated>
		<difficult>0</difficult>
		<occluded>0</occluded>
		<bndbox>
			<xmin>130</xmin>
			<xmax>146</xmax>
			<ymin>277</ymin>
			<ymax>357</ymax>
		</bndbox>
		<polygon>
			<x1>145</x1>
			<y1>304</y1>
			<x2>141</x2>
			<y2>276</y2>
			<x3>140</x3>
			<y3>276</y3>
			<x4>130</x4>
			<y4>278.666667</y4>
			<x5>129</x5>
			<y5>345.333333</y5>
			<x6>140</x6>
			<y6>356</y6>
			<x7>145</x7>
			<y7>304</y7>
		</polygon>
	</object>
	<object>
		<name>desk</name>
		<pose>Unspecified</pose>
		<truncated>0</truncated>
		<difficult>0</difficult>
		<occluded>0</occluded>
		<bndbox>
			<xmin>228</xmin>
			<xmax>317</xmax>
			<ymin>262</ymin>
			<ymax>368</ymax>
		</bndbox>
		<polygon>
			<x1>308</x1>
			<y1>366.666667</y1>
			<x2>315</x2>
			<y2>353.333333</y2>
			<x3>316</x3>
			<y3>333.333333</y3>
			<x4>313</x4>
			<y4>285.333333</y4>
			<x5>309</x5>
			<y5>273.333333</y5>
			<x6>291</x6>
			<y6>274.666667</y6>
			<x7>273</x7>
			<y7>264</y7>
			<x8>248</x8>
			<y8>261.333333</y8>
			<x9>246</x9>
			<y9>261.333333</y9>
			<x10>244</x10>
			<y10>290.666667</y10>
			<x11>227</x11>
			<y11>289.333333</y11>
			<x12>229</x12>
			<y12>366.666667</y12>
			<x13>308</x13>
			<y13>366.666667</y13>
		</polygon>
	</object>
	<object>
		<name>table</name>
		<pose>Unspecified</pose>
		<truncated>0</truncated>
		<difficult>0</difficult>
		<occluded>0</occluded>
		<bndbox>
			<xmin>334</xmin>
			<xmax>364</xmax>
			<ymin>232</ymin>
			<ymax>369</ymax>
		</bndbox>
		<polygon>
			<x1>360</x1>
			<y1>368</y1>
			<x2>363</x2>
			<y2>362.666667</y2>
			<x3>350</x3>
			<y3>338.666667</y3>
			<x4>345</x4>
			<y4>302.666667</y4>
			<x5>347</x5>
			<y5>264</y5>
			<x6>358</x6>
			<y6>238.666667</y6>
			<x7>352</x7>
			<y7>230.666667</y7>
			<x8>345.5</x8>
			<y8>230.666667</y8>
			<x9>338</x9>
			<y9>233.333333</y9>
			<x10>333</x10>
			<y10>297.333333</y10>
			<x11>344</x11>
			<y11>362.666667</y11>
			<x12>360</x12>
			<y12>368</y12>
		</polygon>
	</object>
	<object>
		<name>tiled floor</name>
		<pose>Unspecified</pose>
		<truncated>0</truncated>
		<difficult>0</difficult>
		<occluded>0</occluded>
		<bndbox>
			<xmin>1</xmin>
			<xmax>640</xmax>
			<ymin>346</ymin>
			<ymax>640</ymax>
		</bndbox>
		<polygon>
			<x1>0</x1>
			<y1>638.666667</y1>
			<x2>639</x2>
			<y2>638.666667</y2>
			<x3>639</x3>
			<y3>404</y3>
			<x4>637</x4>
			<y4>365.333333</y4>
			<x5>632</x5>
			<y5>346.666667</y5>
			<x6>631</x6>
			<y6>345.333333</y6>
			<x7>627</x7>
			<y7>352</y7>
			<x8>564</x8>
			<y8>349.333333</y8>
			<x9>555</x9>
			<y9>352</y9>
			<x10>548</x10>
			<y10>362.666667</y10>
			<x11>386</x11>
			<y11>366.666667</y11>
			<x12>374</x12>
			<y12>374.666667</y12>
			<x13>348</x13>
			<y13>370.666667</y13>
			<x14>331</x14>
			<y14>382.666667</y14>
			<x15>299</x15>
			<y15>377.333333</y15>
			<x16>291</x16>
			<y16>382.666667</y16>
			<x17>247</x17>
			<y17>384</y17>
			<x18>210</x18>
			<y18>393.333333</y18>
			<x19>191</x19>
			<y19>388</y19>
			<x20>170</x20>
			<y20>390.666667</y20>
			<x21>162</x21>
			<y21>382.666667</y21>
			<x22>152</x22>
			<y22>389.333333</y22>
			<x23>155</x23>
			<y23>398.666667</y23>
			<x24>153</x24>
			<y24>412</y24>
			<x25>101</x25>
			<y25>410.666667</y25>
			<x26>60</x26>
			<y26>422.666667</y26>
			<x27>34</x27>
			<y27>410.666667</y27>
			<x28>3</x28>
			<y28>410.666667</y28>
			<x29>0</x29>
			<y29>414.666667</y29>
			<x30>0</x30>
			<y30>638.666667</y30>
		</polygon>
	</object>
	<object>
		<name>light bulb</name>
		<pose>Unspecified</pose>
		<truncated>0</truncated>
		<difficult>0</difficult>
		<occluded>0</occluded>
		<bndbox>
			<xmin>55</xmin>
			<xmax>60</xmax>
			<ymin>16</ymin>
			<ymax>29</ymax>
		</bndbox>
		<polygon>
			<x1>58</x1>
			<y1>14.666667</y1>
			<x2>57</x2>
			<y2>14.666667</y2>
			<x3>54</x3>
			<y3>18.666667</y3>
			<x4>56</x4>
			<y4>28</y4>
			<x5>59</x5>
			<y5>25.333333</y5>
			<x6>58</x6>
			<y6>14.666667</y6>
		</polygon>
	</object>
</annotation>
