<annotation>
	<folder></folder>
	<filename>frame_000972_png.rf.b3eb8709f24e02ad6a817302c76abb62.jpg</filename>
	<path>frame_000972_png.rf.b3eb8709f24e02ad6a817302c76abb62.jpg</path>
	<source>
		<database>roboflow.com</database>
	</source>
	<size>
		<width>640</width>
		<height>640</height>
		<depth>3</depth>
	</size>
	<segmented>0</segmented>
	<object>
		<name>light bulb</name>
		<pose>Unspecified</pose>
		<truncated>0</truncated>
		<difficult>0</difficult>
		<occluded>0</occluded>
		<bndbox>
			<xmin>392</xmin>
			<xmax>440</xmax>
			<ymin>56</ymin>
			<ymax>84</ymax>
		</bndbox>
		<polygon>
			<x1>414.375</x1>
			<y1>55</y1>
			<x2>398.125</x2>
			<y2>60</y2>
			<x3>391.25</x3>
			<y3>67.5</y3>
			<x4>391.25</x4>
			<y4>75.833333</y4>
			<x5>395.625</x5>
			<y5>80</y5>
			<x6>415</x6>
			<y6>82.5</y6>
			<x7>438.125</x7>
			<y7>75</y7>
			<x8>438.75</x8>
			<y8>64.166667</y8>
			<x9>430.625</x9>
			<y9>56.666667</y9>
			<x10>414.375</x10>
			<y10>55</y10>
		</polygon>
	</object>
	<object>
		<name>light bulb</name>
		<pose>Unspecified</pose>
		<truncated>0</truncated>
		<difficult>0</difficult>
		<occluded>0</occluded>
		<bndbox>
			<xmin>392</xmin>
			<xmax>441</xmax>
			<ymin>56</ymin>
			<ymax>84</ymax>
		</bndbox>
		<polygon>
			<x1>430.625</x1>
			<y1>56.666667</y1>
			<x2>414.375</x2>
			<y2>55</y2>
			<x3>398.125</x3>
			<y3>60</y3>
			<x4>391.25</x4>
			<y4>67.5</y4>
			<x5>391.25</x5>
			<y5>75.833333</y5>
			<x6>395.625</x6>
			<y6>80</y6>
			<x7>416.25</x7>
			<y7>82.5</y7>
			<x8>434.375</x8>
			<y8>78.333333</y8>
			<x9>440</x9>
			<y9>72.5</y9>
			<x10>438.75</x10>
			<y10>64.166667</y10>
			<x11>430.625</x11>
			<y11>56.666667</y11>
		</polygon>
	</object>
	<object>
		<name>person</name>
		<pose>Unspecified</pose>
		<truncated>0</truncated>
		<difficult>0</difficult>
		<occluded>0</occluded>
		<bndbox>
			<xmin>1</xmin>
			<xmax>301</xmax>
			<ymin>1</ymin>
			<ymax>559</ymax>
		</bndbox>
		<polygon>
			<x1>85.625</x1>
			<y1>0</y1>
			<x2>56.25</x2>
			<y2>10.833333</y2>
			<x3>55</x3>
			<y3>59.166667</y3>
			<x4>43.75</x4>
			<y4>89.166667</y4>
			<x5>32.5</x5>
			<y5>150.833333</y5>
			<x6>22.5</x6>
			<y6>172.5</y6>
			<x7>0</x7>
			<y7>252.5</y7>
			<x8>0</x8>
			<y8>339.166667</y8>
			<x9>20.625</x9>
			<y9>348.333333</y9>
			<x10>31.875</x10>
			<y10>341.666667</y10>
			<x11>52.5</x11>
			<y11>345.833333</y11>
			<x12>47.5</x12>
			<y12>379.166667</y12>
			<x13>51.25</x13>
			<y13>482.5</y13>
			<x14>41.25</x14>
			<y14>504.166667</y14>
			<x15>36.25</x15>
			<y15>552.5</y15>
			<x16>55</x16>
			<y16>557.5</y16>
			<x17>71.875</x17>
			<y17>555</y17>
			<x18>77.5</x18>
			<y18>549.166667</y18>
			<x19>71.25</x19>
			<y19>469.166667</y19>
			<x20>91.25</x20>
			<y20>394.166667</y20>
			<x21>91.25</x21>
			<y21>349.166667</y21>
			<x22>104.375</x22>
			<y22>340</y22>
			<x23>114.375</x23>
			<y23>340</y23>
			<x24>120.625</x24>
			<y24>348.333333</y24>
			<x25>144.375</x25>
			<y25>355</y25>
			<x26>195</x26>
			<y26>357.5</y26>
			<x27>197.5</x27>
			<y27>394.166667</y27>
			<x28>212.5</x28>
			<y28>454.166667</y28>
			<x29>211.25</x29>
			<y29>500.833333</y29>
			<x30>215.625</x30>
			<y30>526.666667</y30>
			<x31>274.375</x31>
			<y31>521.666667</y31>
			<x32>285.625</x32>
			<y32>516.666667</y32>
			<x33>300</x33>
			<y33>500.833333</y33>
			<x34>294.375</x34>
			<y34>488.333333</y34>
			<x35>281.875</x35>
			<y35>488.333333</y35>
			<x36>259.375</x36>
			<y36>478.333333</y36>
			<x37>238.75</x37>
			<y37>457.5</y37>
			<x38>228.75</x38>
			<y38>305.833333</y38>
			<x39>216.25</x39>
			<y39>232.5</y39>
			<x40>176.25</x40>
			<y40>74.166667</y40>
			<x41>176.875</x41>
			<y41>63.333333</y41>
			<x42>195.625</x42>
			<y42>58.333333</y42>
			<x43>200</x43>
			<y43>52.5</y43>
			<x44>200</x44>
			<y44>40.833333</y44>
			<x45>191.25</x45>
			<y45>25.833333</y45>
			<x46>190.625</x46>
			<y46>0</y46>
			<x47>85.625</x47>
			<y47>0</y47>
		</polygon>
	</object>
	<object>
		<name>light bulb</name>
		<pose>Unspecified</pose>
		<truncated>0</truncated>
		<difficult>0</difficult>
		<occluded>0</occluded>
		<bndbox>
			<xmin>1</xmin>
			<xmax>22</xmax>
			<ymin>159</ymin>
			<ymax>171</ymax>
		</bndbox>
		<polygon>
			<x1>0</x1>
			<y1>162.5</y1>
			<x2>4.375</x2>
			<y2>170</y2>
			<x3>20</x3>
			<y3>169.166667</y3>
			<x4>21.25</x4>
			<y4>164.166667</y4>
			<x5>16.875</x5>
			<y5>160</y5>
			<x6>4.375</x6>
			<y6>158.333333</y6>
			<x7>0</x7>
			<y7>162.5</y7>
		</polygon>
	</object>
	<object>
		<name>staircase</name>
		<pose>Unspecified</pose>
		<truncated>0</truncated>
		<difficult>0</difficult>
		<occluded>0</occluded>
		<bndbox>
			<xmin>345</xmin>
			<xmax>641</xmax>
			<ymin>184</ymin>
			<ymax>389</ymax>
		</bndbox>
		<polygon>
			<x1>449.375</x1>
			<y1>193.333333</y1>
			<x2>343.75</x2>
			<y2>282.5</y2>
			<x3>343.75</x3>
			<y3>325.833333</y3>
			<x4>350.625</x4>
			<y4>336.666667</y4>
			<x5>465</x5>
			<y5>387.5</y5>
			<x6>639.375</x6>
			<y6>385</y6>
			<x7>640</x7>
			<y7>184.166667</y7>
			<x8>469.375</x8>
			<y8>183.333333</y8>
			<x9>449.375</x9>
			<y9>193.333333</y9>
		</polygon>
	</object>
	<object>
		<name>tiled floor</name>
		<pose>Unspecified</pose>
		<truncated>0</truncated>
		<difficult>0</difficult>
		<occluded>0</occluded>
		<bndbox>
			<xmin>1</xmin>
			<xmax>641</xmax>
			<ymin>328</ymin>
			<ymax>639</ymax>
		</bndbox>
		<polygon>
			<x1>640</x1>
			<y1>414.166667</y1>
			<x2>635.625</x2>
			<y2>411.666667</y2>
			<x3>628.125</x3>
			<y3>411.666667</y3>
			<x4>624.375</x4>
			<y4>423.333333</y4>
			<x5>616.875</x5>
			<y5>423.333333</y5>
			<x6>611.875</x6>
			<y6>411.666667</y6>
			<x7>608.125</x7>
			<y7>420</y7>
			<x8>593.125</x8>
			<y8>421.666667</y8>
			<x9>548.125</x9>
			<y9>421.666667</y9>
			<x10>536.875</x10>
			<y10>416.666667</y10>
			<x11>533.125</x11>
			<y11>421.666667</y11>
			<x12>459.375</x12>
			<y12>421.666667</y12>
			<x13>364.375</x13>
			<y13>358.333333</y13>
			<x14>341.875</x14>
			<y14>341.666667</y14>
			<x15>335.625</x15>
			<y15>331.666667</y15>
			<x16>320.625</x16>
			<y16>333.333333</y16>
			<x17>310.625</x17>
			<y17>326.666667</y17>
			<x18>243.125</x18>
			<y18>331.666667</y18>
			<x19>236.25</x19>
			<y19>337.5</y19>
			<x20>235</x20>
			<y20>357.5</y20>
			<x21>241.25</x21>
			<y21>452.5</y21>
			<x22>264.375</x22>
			<y22>476.666667</y22>
			<x23>295.625</x23>
			<y23>486.666667</y23>
			<x24>301.25</x24>
			<y24>494.166667</y24>
			<x25>301.25</x25>
			<y25>502.5</y25>
			<x26>293.125</x26>
			<y26>515</y26>
			<x27>275.625</x27>
			<y27>525</y27>
			<x28>220.625</x28>
			<y28>531.666667</y28>
			<x29>212.5</x29>
			<y29>524.166667</y29>
			<x30>210</x30>
			<y30>450.833333</y30>
			<x31>195</x31>
			<y31>394.166667</y31>
			<x32>192.5</x32>
			<y32>362.5</y32>
			<x33>123.125</x33>
			<y33>351.666667</y33>
			<x34>106.875</x34>
			<y34>353.333333</y34>
			<x35>99.375</x35>
			<y35>348.333333</y35>
			<x36>95</x36>
			<y36>354.166667</y36>
			<x37>92.5</x37>
			<y37>399.166667</y37>
			<x38>73.75</x38>
			<y38>465.833333</y38>
			<x39>78.75</x39>
			<y39>550.833333</y39>
			<x40>66.875</x40>
			<y40>560</y40>
			<x41>44.375</x41>
			<y41>561.666667</y41>
			<x42>33.75</x42>
			<y42>550.833333</y42>
			<x43>33.75</x43>
			<y43>530.833333</y43>
			<x44>48.75</x44>
			<y44>474.166667</y44>
			<x45>47.5</x45>
			<y45>357.5</y45>
			<x46>44.375</x46>
			<y46>353.333333</y46>
			<x47>10.625</x47>
			<y47>353.333333</y47>
			<x48>0</x48>
			<y48>364.166667</y48>
			<x49>1.875</x49>
			<y49>638.333333</y49>
			<x50>640</x50>
			<y50>637.5</y50>
			<x51>640</x51>
			<y51>414.166667</y51>
		</polygon>
	</object>
	<object>
		<name>light bulb</name>
		<pose>Unspecified</pose>
		<truncated>0</truncated>
		<difficult>0</difficult>
		<occluded>0</occluded>
		<bndbox>
			<xmin>572</xmin>
			<xmax>622</xmax>
			<ymin>61</ymin>
			<ymax>84</ymax>
		</bndbox>
		<polygon>
			<x1>595.625</x1>
			<y1>60</y1>
			<x2>571.25</x2>
			<y2>70.833333</y2>
			<x3>575.625</x3>
			<y3>81.666667</y3>
			<x4>598.75</x4>
			<y4>82.5</y4>
			<x5>618.125</x5>
			<y5>76.666667</y5>
			<x6>621.25</x6>
			<y6>67.5</y6>
			<x7>613.125</x7>
			<y7>61.666667</y7>
			<x8>595.625</x8>
			<y8>60</y8>
		</polygon>
	</object>
	<object>
		<name>light bulb</name>
		<pose>Unspecified</pose>
		<truncated>0</truncated>
		<difficult>0</difficult>
		<occluded>0</occluded>
		<bndbox>
			<xmin>415</xmin>
			<xmax>420</xmax>
			<ymin>23</ymin>
			<ymax>37</ymax>
		</bndbox>
		<polygon>
			<x1>417.5</x1>
			<y1>35.833333</y1>
			<x2>418.75</x2>
			<y2>24.166667</y2>
			<x3>414.375</x3>
			<y3>21.666667</y3>
			<x4>413.75</x4>
			<y4>35.833333</y4>
			<x5>417.5</x5>
			<y5>35.833333</y5>
		</polygon>
	</object>
	<object>
		<name>light bulb</name>
		<pose>Unspecified</pose>
		<truncated>0</truncated>
		<difficult>0</difficult>
		<occluded>0</occluded>
		<bndbox>
			<xmin>17</xmin>
			<xmax>30</xmax>
			<ymin>146</ymin>
			<ymax>157</ymax>
		</bndbox>
		<polygon>
			<x1>28.75</x1>
			<y1>155.833333</y1>
			<x2>29.375</x2>
			<y2>145</y2>
			<x3>16.25</x3>
			<y3>147.5</y3>
			<x4>18.125</x4>
			<y4>155</y4>
			<x5>28.75</x5>
			<y5>155.833333</y5>
		</polygon>
	</object>
	<object>
		<name>light bulb</name>
		<pose>Unspecified</pose>
		<truncated>0</truncated>
		<difficult>0</difficult>
		<occluded>0</occluded>
		<bndbox>
			<xmin>214</xmin>
			<xmax>264</xmax>
			<ymin>56</ymin>
			<ymax>80</ymax>
		</bndbox>
		<polygon>
			<x1>225.625</x1>
			<y1>55</y1>
			<x2>212.5</x2>
			<y2>62.5</y2>
			<x3>212.5</x3>
			<y3>70.833333</y3>
			<x4>221.875</x4>
			<y4>78.333333</y4>
			<x5>252.5</x5>
			<y5>79.166667</y5>
			<x6>262.5</x6>
			<y6>72.5</y6>
			<x7>262.5</x7>
			<y7>65.833333</y7>
			<x8>255.625</x8>
			<y8>58.333333</y8>
			<x9>225.625</x9>
			<y9>55</y9>
		</polygon>
	</object>
	<object>
		<name>person</name>
		<pose>Unspecified</pose>
		<truncated>0</truncated>
		<difficult>0</difficult>
		<occluded>0</occluded>
		<bndbox>
			<xmin>337</xmin>
			<xmax>359</xmax>
			<ymin>246</ymin>
			<ymax>332</ymax>
		</bndbox>
		<polygon>
			<x1>349.375</x1>
			<y1>245</y1>
			<x2>336.25</x2>
			<y2>270.833333</y2>
			<x3>338.75</x3>
			<y3>330.833333</y3>
			<x4>342.5</x4>
			<y4>324.166667</y4>
			<x5>342.5</x5>
			<y5>275.833333</y5>
			<x6>357.5</x6>
			<y6>264.166667</y6>
			<x7>349.375</x7>
			<y7>245</y7>
		</polygon>
	</object>
</annotation>
