<annotation>
	<folder></folder>
	<filename>frame_000074_png.rf.602e61535b8c76bfb7ceb2e21b69e0d7.jpg</filename>
	<path>frame_000074_png.rf.602e61535b8c76bfb7ceb2e21b69e0d7.jpg</path>
	<source>
		<database>roboflow.com</database>
	</source>
	<size>
		<width>640</width>
		<height>640</height>
		<depth>3</depth>
	</size>
	<segmented>0</segmented>
	<object>
		<name>pillar</name>
		<pose>Unspecified</pose>
		<truncated>0</truncated>
		<difficult>0</difficult>
		<occluded>0</occluded>
		<bndbox>
			<xmin>432</xmin>
			<xmax>500</xmax>
			<ymin>1</ymin>
			<ymax>390</ymax>
		</bndbox>
		<polygon>
			<x1>435</x1>
			<y1>0</y1>
			<x2>432</x2>
			<y2>53.333333</y2>
			<x3>434</x3>
			<y3>112</y3>
			<x4>431</x4>
			<y4>125.333333</y4>
			<x5>431</x5>
			<y5>238.666667</y5>
			<x6>433</x6>
			<y6>245.333333</y6>
			<x7>450</x7>
			<y7>245.333333</y7>
			<x8>455</x8>
			<y8>260</y8>
			<x9>455</x9>
			<y9>378.666667</y9>
			<x10>463</x10>
			<y10>386.666667</y10>
			<x11>491</x11>
			<y11>389.333333</y11>
			<x12>495</x12>
			<y12>386.666667</y12>
			<x13>499</x13>
			<y13>0</y13>
			<x14>493.666667</x14>
			<y14>0</y14>
			<x15>435</x15>
			<y15>0</y15>
		</polygon>
	</object>
	<object>
		<name>door</name>
		<pose>Unspecified</pose>
		<truncated>0</truncated>
		<difficult>0</difficult>
		<occluded>0</occluded>
		<bndbox>
			<xmin>300</xmin>
			<xmax>325</xmax>
			<ymin>258</ymin>
			<ymax>329</ymax>
		</bndbox>
		<polygon>
			<x1>324</x1>
			<y1>326.666667</y1>
			<x2>324</x2>
			<y2>261.333333</y2>
			<x3>321</x3>
			<y3>257.333333</y3>
			<x4>312</x4>
			<y4>257.333333</y4>
			<x5>301</x5>
			<y5>258.666667</y5>
			<x6>299</x6>
			<y6>265.333333</y6>
			<x7>302</x7>
			<y7>328</y7>
			<x8>324</x8>
			<y8>326.666667</y8>
		</polygon>
	</object>
	<object>
		<name>tiled floor</name>
		<pose>Unspecified</pose>
		<truncated>0</truncated>
		<difficult>0</difficult>
		<occluded>0</occluded>
		<bndbox>
			<xmin>1</xmin>
			<xmax>640</xmax>
			<ymin>334</ymin>
			<ymax>640</ymax>
		</bndbox>
		<polygon>
			<x1>0</x1>
			<y1>638.666667</y1>
			<x2>639</x2>
			<y2>638.666667</y2>
			<x3>639</x3>
			<y3>386.666667</y3>
			<x4>591</x4>
			<y4>377.333333</y4>
			<x5>590</x5>
			<y5>369.333333</y5>
			<x6>600</x6>
			<y6>368</y6>
			<x7>601</x7>
			<y7>362.666667</y7>
			<x8>597</x8>
			<y8>360</y8>
			<x9>583</x9>
			<y9>365.333333</y9>
			<x10>568</x10>
			<y10>356</y10>
			<x11>535</x11>
			<y11>354.666667</y11>
			<x12>528</x12>
			<y12>361.333333</y12>
			<x13>515</x13>
			<y13>354.666667</y13>
			<x14>499</x14>
			<y14>364</y14>
			<x15>499</x15>
			<y15>402.666667</y15>
			<x16>496</x16>
			<y16>406.666667</y16>
			<x17>491</x17>
			<y17>400</y17>
			<x18>488</x18>
			<y18>409.333333</y18>
			<x19>468</x19>
			<y19>405.333333</y19>
			<x20>461</x20>
			<y20>410.666667</y20>
			<x21>405</x21>
			<y21>408</y21>
			<x22>380</x22>
			<y22>378.666667</y22>
			<x23>386</x23>
			<y23>352</y23>
			<x24>378</x24>
			<y24>342.666667</y24>
			<x25>365</x25>
			<y25>346.666667</y25>
			<x26>348</x26>
			<y26>334.666667</y26>
			<x27>320</x27>
			<y27>333.333333</y27>
			<x28>315</x28>
			<y28>333.333333</y28>
			<x29>306</x29>
			<y29>336</y29>
			<x30>304</x30>
			<y30>341.333333</y30>
			<x31>309</x31>
			<y31>368</y31>
			<x32>290</x32>
			<y32>380</y32>
			<x33>253</x33>
			<y33>380</y33>
			<x34>249</x34>
			<y34>368</y34>
			<x35>251</x35>
			<y35>353.333333</y35>
			<x36>245</x36>
			<y36>350.666667</y36>
			<x37>245</x37>
			<y37>342.666667</y37>
			<x38>238</x38>
			<y38>340</y38>
			<x39>223</x39>
			<y39>349.333333</y39>
			<x40>218</x40>
			<y40>384</y40>
			<x41>209</x41>
			<y41>377.333333</y41>
			<x42>209</x42>
			<y42>360</y42>
			<x43>205</x43>
			<y43>357.333333</y43>
			<x44>208</x44>
			<y44>350.666667</y44>
			<x45>196</x45>
			<y45>348</y45>
			<x46>183</x46>
			<y46>356</y46>
			<x47>179</x47>
			<y47>374.666667</y47>
			<x48>169</x48>
			<y48>370.666667</y48>
			<x49>151</x49>
			<y49>374.666667</y49>
			<x50>144</x50>
			<y50>388</y50>
			<x51>139</x51>
			<y51>380</y51>
			<x52>119</x52>
			<y52>374.666667</y52>
			<x53>111</x53>
			<y53>377.333333</y53>
			<x54>104</x54>
			<y54>369.333333</y54>
			<x55>61</x55>
			<y55>368</y55>
			<x56>56</x56>
			<y56>372</y56>
			<x57>50</x57>
			<y57>368</y57>
			<x58>46</x58>
			<y58>372</y58>
			<x59>35</x59>
			<y59>368</y59>
			<x60>26</x60>
			<y60>372</y60>
			<x61>23</x61>
			<y61>361.333333</y61>
			<x62>3</x62>
			<y62>364</y62>
			<x63>0</x63>
			<y63>368</y63>
			<x64>0</x64>
			<y64>638.666667</y64>
		</polygon>
	</object>
	<object>
		<name>light bulb</name>
		<pose>Unspecified</pose>
		<truncated>0</truncated>
		<difficult>0</difficult>
		<occluded>0</occluded>
		<bndbox>
			<xmin>245</xmin>
			<xmax>304</xmax>
			<ymin>16</ymin>
			<ymax>54</ymax>
		</bndbox>
		<polygon>
			<x1>259</x1>
			<y1>50.666667</y1>
			<x2>275</x2>
			<y2>53.333333</y2>
			<x3>293</x3>
			<y3>50.666667</y3>
			<x4>303</x4>
			<y4>41.333333</y4>
			<x5>303</x5>
			<y5>32</y5>
			<x6>297</x6>
			<y6>21.333333</y6>
			<x7>279</x7>
			<y7>16</y7>
			<x8>278</x8>
			<y8>14.666667</y8>
			<x9>258</x9>
			<y9>17.333333</y9>
			<x10>248</x10>
			<y10>24</y10>
			<x11>244</x11>
			<y11>38.666667</y11>
			<x12>259</x12>
			<y12>50.666667</y12>
		</polygon>
	</object>
	<object>
		<name>light bulb</name>
		<pose>Unspecified</pose>
		<truncated>0</truncated>
		<difficult>0</difficult>
		<occluded>0</occluded>
		<bndbox>
			<xmin>425</xmin>
			<xmax>433</xmax>
			<ymin>97</ymin>
			<ymax>116</ymax>
		</bndbox>
		<polygon>
			<x1>431</x1>
			<y1>96</y1>
			<x2>430</x2>
			<y2>96</y2>
			<x3>424</x3>
			<y3>105.333333</y3>
			<x4>429</x4>
			<y4>114.666667</y4>
			<x5>432</x5>
			<y5>113.333333</y5>
			<x6>431</x6>
			<y6>96</y6>
		</polygon>
	</object>
	<object>
		<name>light bulb</name>
		<pose>Unspecified</pose>
		<truncated>0</truncated>
		<difficult>0</difficult>
		<occluded>0</occluded>
		<bndbox>
			<xmin>34</xmin>
			<xmax>71</xmax>
			<ymin>124</ymin>
			<ymax>140</ymax>
		</bndbox>
		<polygon>
			<x1>70</x1>
			<y1>134.666667</y1>
			<x2>69</x2>
			<y2>128</y2>
			<x3>48</x3>
			<y3>122.666667</y3>
			<x4>44</x4>
			<y4>122.666667</y4>
			<x5>34</x5>
			<y5>125.333333</y5>
			<x6>33</x6>
			<y6>130.666667</y6>
			<x7>53</x7>
			<y7>138.666667</y7>
			<x8>70</x8>
			<y8>134.666667</y8>
		</polygon>
	</object>
	<object>
		<name>light bulb</name>
		<pose>Unspecified</pose>
		<truncated>0</truncated>
		<difficult>0</difficult>
		<occluded>0</occluded>
		<bndbox>
			<xmin>1</xmin>
			<xmax>24</xmax>
			<ymin>138</ymin>
			<ymax>152</ymax>
		</bndbox>
		<polygon>
			<x1>0</x1>
			<y1>150.666667</y1>
			<x2>23</x2>
			<y2>149.333333</y2>
			<x3>21</x3>
			<y3>141.333333</y3>
			<x4>8</x4>
			<y4>137.333333</y4>
			<x5>0</x5>
			<y5>137.333333</y5>
			<x6>0</x6>
			<y6>150.666667</y6>
		</polygon>
	</object>
	<object>
		<name>light bulb</name>
		<pose>Unspecified</pose>
		<truncated>0</truncated>
		<difficult>0</difficult>
		<occluded>0</occluded>
		<bndbox>
			<xmin>74</xmin>
			<xmax>81</xmax>
			<ymin>181</ymin>
			<ymax>190</ymax>
		</bndbox>
		<polygon>
			<x1>78</x1>
			<y1>180</y1>
			<x2>73</x2>
			<y2>185.333333</y2>
			<x3>80</x3>
			<y3>189.333333</y3>
			<x4>79</x4>
			<y4>181.333333</y4>
			<x5>78</x5>
			<y5>180</y5>
		</polygon>
	</object>
	<object>
		<name>light bulb</name>
		<pose>Unspecified</pose>
		<truncated>0</truncated>
		<difficult>0</difficult>
		<occluded>0</occluded>
		<bndbox>
			<xmin>127</xmin>
			<xmax>144</xmax>
			<ymin>176</ymin>
			<ymax>185</ymax>
		</bndbox>
		<polygon>
			<x1>143</x1>
			<y1>178.666667</y1>
			<x2>137</x2>
			<y2>174.666667</y2>
			<x3>131.5</x3>
			<y3>174.666667</y3>
			<x4>126</x4>
			<y4>174.666667</y4>
			<x5>126</x5>
			<y5>182.666667</y5>
			<x6>141</x6>
			<y6>184</y6>
			<x7>143</x7>
			<y7>178.666667</y7>
		</polygon>
	</object>
	<object>
		<name>table</name>
		<pose>Unspecified</pose>
		<truncated>0</truncated>
		<difficult>0</difficult>
		<occluded>0</occluded>
		<bndbox>
			<xmin>102</xmin>
			<xmax>227</xmax>
			<ymin>233</ymin>
			<ymax>384</ymax>
		</bndbox>
		<polygon>
			<x1>101</x1>
			<y1>293.333333</y1>
			<x2>111</x2>
			<y2>296</y2>
			<x3>109</x3>
			<y3>308</y3>
			<x4>103</x4>
			<y4>310.666667</y4>
			<x5>108</x5>
			<y5>314.666667</y5>
			<x6>109</x6>
			<y6>337.333333</y6>
			<x7>101</x7>
			<y7>340</y7>
			<x8>101</x8>
			<y8>365.333333</y8>
			<x9>108</x9>
			<y9>364</y9>
			<x10>113</x10>
			<y10>370.666667</y10>
			<x11>118</x11>
			<y11>364</y11>
			<x12>129</x12>
			<y12>365.333333</y12>
			<x13>136</x13>
			<y13>358.666667</y13>
			<x14>141</x14>
			<y14>382.666667</y14>
			<x15>147</x15>
			<y15>378.666667</y15>
			<x16>149</x16>
			<y16>365.333333</y16>
			<x17>165</x17>
			<y17>364</y17>
			<x18>178</x18>
			<y18>369.333333</y18>
			<x19>179</x19>
			<y19>294.666667</y19>
			<x20>188</x20>
			<y20>290.666667</y20>
			<x21>209</x21>
			<y21>298.666667</y21>
			<x22>212</x22>
			<y22>374.666667</y22>
			<x23>218</x23>
			<y23>376</y23>
			<x24>219</x24>
			<y24>289.333333</y24>
			<x25>226</x25>
			<y25>282.666667</y25>
			<x26>225</x26>
			<y26>274.666667</y26>
			<x27>171</x27>
			<y27>272</y27>
			<x28>164</x28>
			<y28>262.666667</y28>
			<x29>170</x29>
			<y29>249.333333</y29>
			<x30>161</x30>
			<y30>242.666667</y30>
			<x31>158</x31>
			<y31>246.666667</y31>
			<x32>114</x32>
			<y32>244</y32>
			<x33>104</x33>
			<y33>233.333333</y33>
			<x34>103</x34>
			<y34>232</y34>
			<x35>101</x35>
			<y35>238.666667</y35>
			<x36>106</x36>
			<y36>257.333333</y36>
			<x37>101</x37>
			<y37>262.666667</y37>
			<x38>101</x38>
			<y38>293.333333</y38>
		</polygon>
	</object>
	<object>
		<name>light bulb</name>
		<pose>Unspecified</pose>
		<truncated>0</truncated>
		<difficult>0</difficult>
		<occluded>0</occluded>
		<bndbox>
			<xmin>189</xmin>
			<xmax>196</xmax>
			<ymin>212</ymin>
			<ymax>217</ymax>
		</bndbox>
		<polygon>
			<x1>189</x1>
			<y1>210.666667</y1>
			<x2>188</x2>
			<y2>216</y2>
			<x3>195</x3>
			<y3>216</y3>
			<x4>194</x4>
			<y4>210.666667</y4>
			<x5>189</x5>
			<y5>210.666667</y5>
		</polygon>
	</object>
	<object>
		<name>person</name>
		<pose>Unspecified</pose>
		<truncated>0</truncated>
		<difficult>0</difficult>
		<occluded>0</occluded>
		<bndbox>
			<xmin>251</xmin>
			<xmax>298</xmax>
			<ymin>146</ymin>
			<ymax>376</ymax>
		</bndbox>
		<polygon>
			<x1>250</x1>
			<y1>233.333333</y1>
			<x2>256</x2>
			<y2>249.333333</y2>
			<x3>258</x3>
			<y3>282.666667</y3>
			<x4>254</x4>
			<y4>370.666667</y4>
			<x5>268</x5>
			<y5>369.333333</y5>
			<x6>279</x6>
			<y6>374.666667</y6>
			<x7>297</x7>
			<y7>370.666667</y7>
			<x8>287</x8>
			<y8>360</y8>
			<x9>278</x9>
			<y9>364</y9>
			<x10>266</x10>
			<y10>353.333333</y10>
			<x11>270</x11>
			<y11>306.666667</y11>
			<x12>274</x12>
			<y12>300</y12>
			<x13>277</x13>
			<y13>302.666667</y13>
			<x14>276</x14>
			<y14>354.666667</y14>
			<x15>279</x15>
			<y15>357.333333</y15>
			<x16>285</x16>
			<y16>348</y16>
			<x17>296</x17>
			<y17>257.333333</y17>
			<x18>289</x18>
			<y18>193.333333</y18>
			<x19>280</x19>
			<y19>177.333333</y19>
			<x20>282</x20>
			<y20>152</y20>
			<x21>277</x21>
			<y21>145.333333</y21>
			<x22>269</x22>
			<y22>145.333333</y22>
			<x23>265</x23>
			<y23>156</y23>
			<x24>266</x24>
			<y24>170.666667</y24>
			<x25>250</x25>
			<y25>200</y25>
			<x26>250</x26>
			<y26>233.333333</y26>
		</polygon>
	</object>
	<object>
		<name>person</name>
		<pose>Unspecified</pose>
		<truncated>0</truncated>
		<difficult>0</difficult>
		<occluded>0</occluded>
		<bndbox>
			<xmin>354</xmin>
			<xmax>373</xmax>
			<ymin>272</ymin>
			<ymax>338</ymax>
		</bndbox>
		<polygon>
			<x1>372</x1>
			<y1>286.666667</y1>
			<x2>363</x2>
			<y2>270.666667</y2>
			<x3>361</x3>
			<y3>270.666667</y3>
			<x4>353</x4>
			<y4>293.333333</y4>
			<x5>364</x5>
			<y5>337.333333</y5>
			<x6>372</x6>
			<y6>308</y6>
			<x7>372</x7>
			<y7>286.666667</y7>
		</polygon>
	</object>
	<object>
		<name>person</name>
		<pose>Unspecified</pose>
		<truncated>0</truncated>
		<difficult>0</difficult>
		<occluded>0</occluded>
		<bndbox>
			<xmin>239</xmin>
			<xmax>257</xmax>
			<ymin>264</ymin>
			<ymax>337</ymax>
		</bndbox>
		<polygon>
			<x1>246</x1>
			<y1>296</y1>
			<x2>247</x2>
			<y2>333.333333</y2>
			<x3>243</x3>
			<y3>336</y3>
			<x4>252</x4>
			<y4>333.333333</y4>
			<x5>255</x5>
			<y5>312</y5>
			<x6>256</x6>
			<y6>278.666667</y6>
			<x7>251</x7>
			<y7>262.666667</y7>
			<x8>249</x8>
			<y8>262.666667</y8>
			<x9>247</x9>
			<y9>273.333333</y9>
			<x10>238</x10>
			<y10>278.666667</y10>
			<x11>238</x11>
			<y11>290.666667</y11>
			<x12>246</x12>
			<y12>296</y12>
		</polygon>
	</object>
	<object>
		<name>light bulb</name>
		<pose>Unspecified</pose>
		<truncated>0</truncated>
		<difficult>0</difficult>
		<occluded>0</occluded>
		<bndbox>
			<xmin>3</xmin>
			<xmax>51</xmax>
			<ymin>62</ymin>
			<ymax>85</ymax>
		</bndbox>
		<polygon>
			<x1>43</x1>
			<y1>84</y1>
			<x2>50</x2>
			<y2>78.666667</y2>
			<x3>48</x3>
			<y3>69.333333</y3>
			<x4>14</x4>
			<y4>62.666667</y4>
			<x5>13</x5>
			<y5>61.333333</y5>
			<x6>2</x6>
			<y6>68</y6>
			<x7>10</x7>
			<y7>78.666667</y7>
			<x8>30</x8>
			<y8>84</y8>
			<x9>43</x9>
			<y9>84</y9>
		</polygon>
	</object>
	<object>
		<name>light bulb</name>
		<pose>Unspecified</pose>
		<truncated>0</truncated>
		<difficult>0</difficult>
		<occluded>0</occluded>
		<bndbox>
			<xmin>500</xmin>
			<xmax>550</xmax>
			<ymin>1</ymin>
			<ymax>52</ymax>
		</bndbox>
		<polygon>
			<x1>517</x1>
			<y1>0</y1>
			<x2>518</x2>
			<y2>9.333333</y2>
			<x3>510</x3>
			<y3>14.666667</y3>
			<x4>500</x4>
			<y4>12</y4>
			<x5>499</x5>
			<y5>42.666667</y5>
			<x6>508</x6>
			<y6>41.333333</y6>
			<x7>512</x7>
			<y7>45.333333</y7>
			<x8>508</x8>
			<y8>50.666667</y8>
			<x9>518</x9>
			<y9>40</y9>
			<x10>538</x10>
			<y10>37.333333</y10>
			<x11>526</x11>
			<y11>30.666667</y11>
			<x12>549</x12>
			<y12>0</y12>
			<x13>543.666667</x13>
			<y13>0</y13>
			<x14>517</x14>
			<y14>0</y14>
		</polygon>
	</object>
	<object>
		<name>light bulb</name>
		<pose>Unspecified</pose>
		<truncated>0</truncated>
		<difficult>0</difficult>
		<occluded>0</occluded>
		<bndbox>
			<xmin>376</xmin>
			<xmax>435</xmax>
			<ymin>1</ymin>
			<ymax>42</ymax>
		</bndbox>
		<polygon>
			<x1>382</x1>
			<y1>0</y1>
			<x2>375</x2>
			<y2>41.333333</y2>
			<x3>431</x3>
			<y3>40</y3>
			<x4>434</x4>
			<y4>0</y4>
			<x5>428.8</x5>
			<y5>0</y5>
			<x6>382</x6>
			<y6>0</y6>
		</polygon>
	</object>
	<object>
		<name>pillar</name>
		<pose>Unspecified</pose>
		<truncated>0</truncated>
		<difficult>0</difficult>
		<occluded>0</occluded>
		<bndbox>
			<xmin>82</xmin>
			<xmax>127</xmax>
			<ymin>84</ymin>
			<ymax>350</ymax>
		</bndbox>
		<polygon>
			<x1>98</x1>
			<y1>349.333333</y1>
			<x2>100</x2>
			<y2>345.333333</y2>
			<x3>100</x3>
			<y3>290.666667</y3>
			<x4>96</x4>
			<y4>276</y4>
			<x5>100</x5>
			<y5>149.333333</y5>
			<x6>105</x6>
			<y6>141.333333</y6>
			<x7>126</x7>
			<y7>138.666667</y7>
			<x8>126</x8>
			<y8>93.333333</y8>
			<x9>118</x9>
			<y9>82.666667</y9>
			<x10>113</x10>
			<y10>82.666667</y10>
			<x11>83</x11>
			<y11>82.666667</y11>
			<x12>81</x12>
			<y12>86.666667</y12>
			<x13>83</x13>
			<y13>349.333333</y13>
			<x14>98</x14>
			<y14>349.333333</y14>
		</polygon>
	</object>
	<object>
		<name>trash bin</name>
		<pose>Unspecified</pose>
		<truncated>0</truncated>
		<difficult>0</difficult>
		<occluded>0</occluded>
		<bndbox>
			<xmin>388</xmin>
			<xmax>460</xmax>
			<ymin>249</ymin>
			<ymax>404</ymax>
		</bndbox>
		<polygon>
			<x1>387</x1>
			<y1>378.666667</y1>
			<x2>406</x2>
			<y2>402.666667</y2>
			<x3>459</x3>
			<y3>401.333333</y3>
			<x4>459</x4>
			<y4>385.333333</y4>
			<x5>455</x5>
			<y5>378.666667</y5>
			<x6>452</x6>
			<y6>250.666667</y6>
			<x7>435</x7>
			<y7>248</y7>
			<x8>429.6</x8>
			<y8>248</y8>
			<x9>408</x9>
			<y9>248</y9>
			<x10>390</x10>
			<y10>266.666667</y10>
			<x11>390</x11>
			<y11>361.333333</y11>
			<x12>387</x12>
			<y12>378.666667</y12>
		</polygon>
	</object>
	<object>
		<name>person</name>
		<pose>Unspecified</pose>
		<truncated>0</truncated>
		<difficult>0</difficult>
		<occluded>0</occluded>
		<bndbox>
			<xmin>17</xmin>
			<xmax>56</xmax>
			<ymin>276</ymin>
			<ymax>344</ymax>
		</bndbox>
		<polygon>
			<x1>28</x1>
			<y1>312</y1>
			<x2>32</x2>
			<y2>304</y2>
			<x3>40</x3>
			<y3>308</y3>
			<x4>36</x4>
			<y4>310.666667</y4>
			<x5>39</x5>
			<y5>342.666667</y5>
			<x6>50</x6>
			<y6>341.333333</y6>
			<x7>55</x7>
			<y7>314.666667</y7>
			<x8>47</x8>
			<y8>304</y8>
			<x9>43</x9>
			<y9>274.666667</y9>
			<x10>40</x10>
			<y10>274.666667</y10>
			<x11>19</x11>
			<y11>305.333333</y11>
			<x12>16</x12>
			<y12>338.666667</y12>
			<x13>29</x13>
			<y13>340</y13>
			<x14>28</x14>
			<y14>312</y14>
		</polygon>
	</object>
</annotation>
