<annotation>
	<folder></folder>
	<filename>frame_001880_png.rf.52c97477b98d4fad43d61179226b9fd2.jpg</filename>
	<path>frame_001880_png.rf.52c97477b98d4fad43d61179226b9fd2.jpg</path>
	<source>
		<database>roboflow.com</database>
	</source>
	<size>
		<width>640</width>
		<height>640</height>
		<depth>3</depth>
	</size>
	<segmented>0</segmented>
	<object>
		<name>person</name>
		<pose>Unspecified</pose>
		<truncated>0</truncated>
		<difficult>0</difficult>
		<occluded>0</occluded>
		<bndbox>
			<xmin>532</xmin>
			<xmax>591</xmax>
			<ymin>184</ymin>
			<ymax>356</ymax>
		</bndbox>
		<polygon>
			<x1>538</x1>
			<y1>314.666667</y1>
			<x2>531</x2>
			<y2>344</y2>
			<x3>535</x3>
			<y3>352</y3>
			<x4>542</x4>
			<y4>350.666667</y4>
			<x5>550</x5>
			<y5>317.333333</y5>
			<x6>561</x6>
			<y6>294.666667</y6>
			<x7>573</x7>
			<y7>352</y7>
			<x8>585</x8>
			<y8>354.666667</y8>
			<x9>590</x9>
			<y9>350.666667</y9>
			<x10>585</x10>
			<y10>345.333333</y10>
			<x11>581</x11>
			<y11>318.666667</y11>
			<x12>577</x12>
			<y12>240</y12>
			<x13>567</x13>
			<y13>210.666667</y13>
			<x14>568</x14>
			<y14>194.666667</y14>
			<x15>564</x15>
			<y15>182.666667</y15>
			<x16>562</x16>
			<y16>182.666667</y16>
			<x17>556</x17>
			<y17>192</y17>
			<x18>557</x18>
			<y18>204</y18>
			<x19>540</x19>
			<y19>220</y19>
			<x20>538</x20>
			<y20>314.666667</y20>
		</polygon>
	</object>
	<object>
		<name>door</name>
		<pose>Unspecified</pose>
		<truncated>0</truncated>
		<difficult>0</difficult>
		<occluded>0</occluded>
		<bndbox>
			<xmin>311</xmin>
			<xmax>542</xmax>
			<ymin>92</ymin>
			<ymax>341</ymax>
		</bndbox>
		<polygon>
			<x1>321</x1>
			<y1>182.666667</y1>
			<x2>323</x2>
			<y2>236</y2>
			<x3>331</x3>
			<y3>234.666667</y3>
			<x4>333</x4>
			<y4>210.666667</y4>
			<x5>323</x5>
			<y5>193.333333</y5>
			<x6>324</x6>
			<y6>184</y6>
			<x7>330</x7>
			<y7>177.333333</y7>
			<x8>342</x8>
			<y8>185.333333</y8>
			<x9>344</x9>
			<y9>197.333333</y9>
			<x10>353</x10>
			<y10>209.333333</y10>
			<x11>353</x11>
			<y11>290.666667</y11>
			<x12>355</x12>
			<y12>298.666667</y12>
			<x13>361</x13>
			<y13>293.333333</y13>
			<x14>367</x14>
			<y14>308</y14>
			<x15>368</x15>
			<y15>340</y15>
			<x16>381</x16>
			<y16>334.666667</y16>
			<x17>478</x17>
			<y17>334.666667</y17>
			<x18>480</x18>
			<y18>330.666667</y18>
			<x19>533</x19>
			<y19>328</y19>
			<x20>538</x20>
			<y20>217.333333</y20>
			<x21>541</x21>
			<y21>210.666667</y21>
			<x22>540</x22>
			<y22>93.333333</y22>
			<x23>524</x23>
			<y23>92</y23>
			<x24>523</x24>
			<y24>90.666667</y24>
			<x25>478</x25>
			<y25>101.333333</y25>
			<x26>310</x26>
			<y26>122.666667</y26>
			<x27>310</x27>
			<y27>169.333333</y27>
			<x28>321</x28>
			<y28>182.666667</y28>
		</polygon>
	</object>
	<object>
		<name>light bulb</name>
		<pose>Unspecified</pose>
		<truncated>0</truncated>
		<difficult>0</difficult>
		<occluded>0</occluded>
		<bndbox>
			<xmin>381</xmin>
			<xmax>412</xmax>
			<ymin>140</ymin>
			<ymax>174</ymax>
		</bndbox>
		<polygon>
			<x1>411</x1>
			<y1>168</y1>
			<x2>386</x2>
			<y2>138.666667</y2>
			<x3>383</x3>
			<y3>138.666667</y3>
			<x4>380</x4>
			<y4>145.333333</y4>
			<x5>398</x5>
			<y5>170.666667</y5>
			<x6>410</x6>
			<y6>173.333333</y6>
			<x7>411</x7>
			<y7>168</y7>
		</polygon>
	</object>
	<object>
		<name>light bulb</name>
		<pose>Unspecified</pose>
		<truncated>0</truncated>
		<difficult>0</difficult>
		<occluded>0</occluded>
		<bndbox>
			<xmin>12</xmin>
			<xmax>46</xmax>
			<ymin>74</ymin>
			<ymax>92</ymax>
		</bndbox>
		<polygon>
			<x1>43</x1>
			<y1>89.333333</y1>
			<x2>45</x2>
			<y2>80</y2>
			<x3>33</x3>
			<y3>73.333333</y3>
			<x4>27.333333</x4>
			<y4>73.333333</y4>
			<x5>13</x5>
			<y5>74.666667</y5>
			<x6>11</x6>
			<y6>81.333333</y6>
			<x7>26</x7>
			<y7>90.666667</y7>
			<x8>43</x8>
			<y8>89.333333</y8>
		</polygon>
	</object>
	<object>
		<name>light bulb</name>
		<pose>Unspecified</pose>
		<truncated>0</truncated>
		<difficult>0</difficult>
		<occluded>0</occluded>
		<bndbox>
			<xmin>1</xmin>
			<xmax>29</xmax>
			<ymin>25</ymin>
			<ymax>48</ymax>
		</bndbox>
		<polygon>
			<x1>0</x1>
			<y1>44</y1>
			<x2>19</x2>
			<y2>46.666667</y2>
			<x3>28</x3>
			<y3>41.333333</y3>
			<x4>25</x4>
			<y4>30.666667</y4>
			<x5>9</x5>
			<y5>24</y5>
			<x6>0</x6>
			<y6>24</y6>
			<x7>0</x7>
			<y7>44</y7>
		</polygon>
	</object>
	<object>
		<name>light bulb</name>
		<pose>Unspecified</pose>
		<truncated>0</truncated>
		<difficult>0</difficult>
		<occluded>0</occluded>
		<bndbox>
			<xmin>471</xmin>
			<xmax>486</xmax>
			<ymin>46</ymin>
			<ymax>61</ymax>
		</bndbox>
		<polygon>
			<x1>485</x1>
			<y1>45.333333</y1>
			<x2>476</x2>
			<y2>45.333333</y2>
			<x3>470</x3>
			<y3>49.333333</y3>
			<x4>471</x4>
			<y4>60</y4>
			<x5>484</x5>
			<y5>58.666667</y5>
			<x6>485</x6>
			<y6>45.333333</y6>
		</polygon>
	</object>
	<object>
		<name>light bulb</name>
		<pose>Unspecified</pose>
		<truncated>0</truncated>
		<difficult>0</difficult>
		<occluded>0</occluded>
		<bndbox>
			<xmin>86</xmin>
			<xmax>96</xmax>
			<ymin>38</ymin>
			<ymax>52</ymax>
		</bndbox>
		<polygon>
			<x1>93</x1>
			<y1>37.333333</y1>
			<x2>88</x2>
			<y2>37.333333</y2>
			<x3>85</x3>
			<y3>42.666667</y3>
			<x4>90</x4>
			<y4>50.666667</y4>
			<x5>95</x5>
			<y5>46.666667</y5>
			<x6>93</x6>
			<y6>37.333333</y6>
		</polygon>
	</object>
	<object>
		<name>desk</name>
		<pose>Unspecified</pose>
		<truncated>0</truncated>
		<difficult>0</difficult>
		<occluded>0</occluded>
		<bndbox>
			<xmin>260</xmin>
			<xmax>316</xmax>
			<ymin>274</ymin>
			<ymax>348</ymax>
		</bndbox>
		<polygon>
			<x1>265.230769</x1>
			<y1>272.615384</y1>
			<x2>259.230769</x2>
			<y2>276.615384</y2>
			<x3>259.230769</x3>
			<y3>303.282051</y3>
			<x4>266.230769</x4>
			<y4>347.282051</y4>
			<x5>304.230769</x5>
			<y5>341.948717</y5>
			<x6>315.230769</x6>
			<y6>345.948717</y6>
			<x7>314.230769</x7>
			<y7>276.615384</y7>
			<x8>306.230769</x8>
			<y8>281.948717</y8>
			<x9>299.230769</x9>
			<y9>275.282051</y9>
			<x10>272.230769</x10>
			<y10>276.615384</y10>
			<x11>265.230769</x11>
			<y11>272.615384</y11>
		</polygon>
	</object>
	<object>
		<name>table</name>
		<pose>Unspecified</pose>
		<truncated>0</truncated>
		<difficult>0</difficult>
		<occluded>0</occluded>
		<bndbox>
			<xmin>300</xmin>
			<xmax>336</xmax>
			<ymin>254</ymin>
			<ymax>353</ymax>
		</bndbox>
		<polygon>
			<x1>331</x1>
			<y1>346.666667</y1>
			<x2>335</x2>
			<y2>341.333333</y2>
			<x3>330</x3>
			<y3>258.666667</y3>
			<x4>322</x4>
			<y4>254.666667</y4>
			<x5>321</x5>
			<y5>253.333333</y5>
			<x6>299</x6>
			<y6>258.666667</y6>
			<x7>315</x7>
			<y7>278.666667</y7>
			<x8>311</x8>
			<y8>352</y8>
			<x9>331</x9>
			<y9>346.666667</y9>
		</polygon>
	</object>
	<object>
		<name>person</name>
		<pose>Unspecified</pose>
		<truncated>0</truncated>
		<difficult>0</difficult>
		<occluded>0</occluded>
		<bndbox>
			<xmin>326</xmin>
			<xmax>354</xmax>
			<ymin>181</ymin>
			<ymax>350</ymax>
		</bndbox>
		<polygon>
			<x1>330</x1>
			<y1>281.333333</y1>
			<x2>337</x2>
			<y2>326.666667</y2>
			<x3>336</x3>
			<y3>348</y3>
			<x4>350</x4>
			<y4>349.333333</y4>
			<x5>353</x5>
			<y5>325.333333</y5>
			<x6>352</x6>
			<y6>213.333333</y6>
			<x7>350</x7>
			<y7>205.333333</y7>
			<x8>340</x8>
			<y8>196</y8>
			<x9>336</x9>
			<y9>180</y9>
			<x10>329</x10>
			<y10>180</y10>
			<x11>325</x11>
			<y11>185.333333</y11>
			<x12>326</x12>
			<y12>196</y12>
			<x13>335</x13>
			<y13>210.666667</y13>
			<x14>330</x14>
			<y14>281.333333</y14>
		</polygon>
	</object>
	<object>
		<name>person</name>
		<pose>Unspecified</pose>
		<truncated>0</truncated>
		<difficult>0</difficult>
		<occluded>0</occluded>
		<bndbox>
			<xmin>48</xmin>
			<xmax>157</xmax>
			<ymin>198</ymin>
			<ymax>374</ymax>
		</bndbox>
		<polygon>
			<x1>132</x1>
			<y1>238.666667</y1>
			<x2>115</x2>
			<y2>250.666667</y2>
			<x3>109</x3>
			<y3>265.333333</y3>
			<x4>100</x4>
			<y4>268</y4>
			<x5>91</x5>
			<y5>288</y5>
			<x6>56</x6>
			<y6>310.666667</y6>
			<x7>47</x7>
			<y7>354.666667</y7>
			<x8>48</x8>
			<y8>365.333333</y8>
			<x9>54</x9>
			<y9>368</y9>
			<x10>51</x10>
			<y10>373.333333</y10>
			<x11>56</x11>
			<y11>370.666667</y11>
			<x12>68</x12>
			<y12>324</y12>
			<x13>73</x13>
			<y13>325.333333</y13>
			<x14>80</x14>
			<y14>314.666667</y14>
			<x15>108</x15>
			<y15>314.666667</y15>
			<x16>113</x16>
			<y16>286.666667</y16>
			<x17>132</x17>
			<y17>266.666667</y17>
			<x18>143</x18>
			<y18>268</y18>
			<x19>151</x19>
			<y19>261.333333</y19>
			<x20>150</x20>
			<y20>244</y20>
			<x21>156</x21>
			<y21>229.333333</y21>
			<x22>153</x22>
			<y22>205.333333</y22>
			<x23>146</x23>
			<y23>197.333333</y23>
			<x24>144</x24>
			<y24>197.333333</y24>
			<x25>132</x25>
			<y25>202.666667</y25>
			<x26>129</x26>
			<y26>216</y26>
			<x27>135</x27>
			<y27>233.333333</y27>
			<x28>132</x28>
			<y28>238.666667</y28>
		</polygon>
	</object>
	<object>
		<name>tiled floor</name>
		<pose>Unspecified</pose>
		<truncated>0</truncated>
		<difficult>0</difficult>
		<occluded>0</occluded>
		<bndbox>
			<xmin>2</xmin>
			<xmax>641</xmax>
			<ymin>340</ymin>
			<ymax>641</ymax>
		</bndbox>
		<polygon>
			<x1>640</x1>
			<y1>424</y1>
			<x2>635</x2>
			<y2>421.333333</y2>
			<x3>637</x3>
			<y3>414.666667</y3>
			<x4>633</x4>
			<y4>414.666667</y4>
			<x5>632</x5>
			<y5>398.666667</y5>
			<x6>625</x6>
			<y6>398.666667</y6>
			<x7>617</x7>
			<y7>382.666667</y7>
			<x8>614</x8>
			<y8>386.666667</y8>
			<x9>606</x9>
			<y9>382.666667</y9>
			<x10>608</x10>
			<y10>374.666667</y10>
			<x11>603</x11>
			<y11>349.333333</y11>
			<x12>596</x12>
			<y12>349.333333</y12>
			<x13>579</x13>
			<y13>364</y13>
			<x14>572</x14>
			<y14>362.666667</y14>
			<x15>567</x15>
			<y15>352</y15>
			<x16>559</x16>
			<y16>350.666667</y16>
			<x17>538</x17>
			<y17>362.666667</y17>
			<x18>526</x18>
			<y18>340</y18>
			<x19>486</x19>
			<y19>340</y19>
			<x20>479</x20>
			<y20>345.333333</y20>
			<x21>472</x21>
			<y21>338.666667</y21>
			<x22>437</x22>
			<y22>340</y22>
			<x23>437</x23>
			<y23>344</y23>
			<x24>430</x24>
			<y24>340</y24>
			<x25>429</x25>
			<y25>338.666667</y25>
			<x26>426</x26>
			<y26>346.666667</y26>
			<x27>419</x27>
			<y27>349.333333</y27>
			<x28>367</x28>
			<y28>350.666667</y28>
			<x29>337</x29>
			<y29>360</y29>
			<x30>315</x30>
			<y30>357.333333</y30>
			<x31>271</x31>
			<y31>362.666667</y31>
			<x32>269</x32>
			<y32>357.333333</y32>
			<x33>266</x33>
			<y33>365.333333</y33>
			<x34>249</x34>
			<y34>366.666667</y34>
			<x35>238</x35>
			<y35>429.333333</y35>
			<x36>258</x36>
			<y36>444</y36>
			<x37>262</x37>
			<y37>461.333333</y37>
			<x38>257</x38>
			<y38>468</y38>
			<x39>226</x39>
			<y39>477.333333</y39>
			<x40>211</x40>
			<y40>477.333333</y40>
			<x41>205.615385</x41>
			<y41>460.820513</y41>
			<x42>194.076923</x42>
			<y42>454.666667</y42>
			<x43>183.307692</x43>
			<y43>421.846153</y43>
			<x44>171.769231</x44>
			<y44>425.948717</y44>
			<x45>168.692308</x45>
			<y45>404.410256</y45>
			<x46>172</x46>
			<y46>398.666667</y46>
			<x47>187.923077</x47>
			<y47>374.666667</y47>
			<x48>156</x48>
			<y48>376</y48>
			<x49>154</x49>
			<y49>382.666667</y49>
			<x50>147</x50>
			<y50>376</y50>
			<x51>125</x51>
			<y51>377.333333</y51>
			<x52>119</x52>
			<y52>386.666667</y52>
			<x53>112</x53>
			<y53>378.666667</y53>
			<x54>103</x54>
			<y54>386.666667</y54>
			<x55>94</x55>
			<y55>386.666667</y55>
			<x56>80</x56>
			<y56>377.333333</y56>
			<x57>74</x57>
			<y57>386.666667</y57>
			<x58>72</x58>
			<y58>378.666667</y58>
			<x59>69</x59>
			<y59>384</y59>
			<x60>61</x60>
			<y60>378.666667</y60>
			<x61>55</x61>
			<y61>385.333333</y61>
			<x62>23</x62>
			<y62>385.333333</y62>
			<x63>19</x63>
			<y63>390.666667</y63>
			<x64>1</x64>
			<y64>384</y64>
			<x65>1</x65>
			<y65>640</y65>
			<x66>640</x66>
			<y66>640</y66>
			<x67>640</x67>
			<y67>424</y67>
		</polygon>
	</object>
	<object>
		<name>chair</name>
		<pose>Unspecified</pose>
		<truncated>0</truncated>
		<difficult>0</difficult>
		<occluded>0</occluded>
		<bndbox>
			<xmin>74</xmin>
			<xmax>153</xmax>
			<ymin>270</ymin>
			<ymax>382</ymax>
		</bndbox>
		<polygon>
			<x1>108</x1>
			<y1>314.666667</y1>
			<x2>91</x2>
			<y2>316</y2>
			<x3>83</x3>
			<y3>310.666667</y3>
			<x4>75</x4>
			<y4>320</y4>
			<x5>73</x5>
			<y5>378.666667</y5>
			<x6>80</x6>
			<y6>357.333333</y6>
			<x7>80</x7>
			<y7>321.333333</y7>
			<x8>104</x8>
			<y8>320</y8>
			<x9>104</x9>
			<y9>376</y9>
			<x10>107</x10>
			<y10>376</y10>
			<x11>108</x11>
			<y11>349.333333</y11>
			<x12>118</x12>
			<y12>381.333333</y12>
			<x13>115</x13>
			<y13>340</y13>
			<x14>115</x14>
			<y14>317.333333</y14>
			<x15>118</x15>
			<y15>314.666667</y15>
			<x16>130</x16>
			<y16>318.974359</y16>
			<x17>132.307692</x17>
			<y17>377.435897</y17>
			<x18>136.923077</x18>
			<y18>311.794872</y18>
			<x19>142.307692</x19>
			<y19>313.846153</y19>
			<x20>152</x20>
			<y20>376</y20>
			<x21>145</x21>
			<y21>313.333333</y21>
			<x22>148</x22>
			<y22>269.333333</y22>
			<x23>139</x23>
			<y23>269.333333</y23>
			<x24>136</x24>
			<y24>269.333333</y24>
			<x25>130</x25>
			<y25>270.666667</y25>
			<x26>128</x26>
			<y26>278.666667</y26>
			<x27>113</x27>
			<y27>292</y27>
			<x28>108</x28>
			<y28>314.666667</y28>
		</polygon>
	</object>
	<object>
		<name>person</name>
		<pose>Unspecified</pose>
		<truncated>0</truncated>
		<difficult>0</difficult>
		<occluded>0</occluded>
		<bndbox>
			<xmin>80</xmin>
			<xmax>105</xmax>
			<ymin>321</ymin>
			<ymax>378</ymax>
		</bndbox>
		<polygon>
			<x1>103</x1>
			<y1>377.333333</y1>
			<x2>104</x2>
			<y2>353.333333</y2>
			<x3>95</x3>
			<y3>341.333333</y3>
			<x4>89</x4>
			<y4>320</y4>
			<x5>80</x5>
			<y5>320</y5>
			<x6>79</x6>
			<y6>336</y6>
			<x7>92</x7>
			<y7>358.666667</y7>
			<x8>91</x8>
			<y8>376</y8>
			<x9>103</x9>
			<y9>377.333333</y9>
		</polygon>
	</object>
	<object>
		<name>person</name>
		<pose>Unspecified</pose>
		<truncated>0</truncated>
		<difficult>0</difficult>
		<occluded>0</occluded>
		<bndbox>
			<xmin>129</xmin>
			<xmax>307</xmax>
			<ymin>1</ymin>
			<ymax>473</ymax>
		</bndbox>
		<polygon>
			<x1>197</x1>
			<y1>0</y1>
			<x2>147</x2>
			<y2>20</y2>
			<x3>128</x3>
			<y3>90.666667</y3>
			<x4>135</x4>
			<y4>138.666667</y4>
			<x5>144</x5>
			<y5>152</y5>
			<x6>174</x6>
			<y6>168</y6>
			<x7>172</x7>
			<y7>186.666667</y7>
			<x8>176</x8>
			<y8>221.333333</y8>
			<x9>214</x9>
			<y9>301.333333</y9>
			<x10>196</x10>
			<y10>337.333333</y10>
			<x11>194</x11>
			<y11>368</y11>
			<x12>169</x12>
			<y12>401.333333</y12>
			<x13>168</x13>
			<y13>410.666667</y13>
			<x14>173</x14>
			<y14>421.333333</y14>
			<x15>182</x15>
			<y15>421.333333</y15>
			<x16>193</x16>
			<y16>454.666667</y16>
			<x17>207</x17>
			<y17>458.666667</y17>
			<x18>209</x18>
			<y18>470.666667</y18>
			<x19>223</x19>
			<y19>472</y19>
			<x20>249</x20>
			<y20>465.333333</y20>
			<x21>259</x21>
			<y21>456</y21>
			<x22>258</x22>
			<y22>448</y22>
			<x23>231</x23>
			<y23>430.666667</y23>
			<x24>246</x24>
			<y24>362.666667</y24>
			<x25>248</x25>
			<y25>310.666667</y25>
			<x26>257</x26>
			<y26>278.666667</y26>
			<x27>259</x27>
			<y27>240</y27>
			<x28>266</x28>
			<y28>236</y28>
			<x29>297</x29>
			<y29>244</y29>
			<x30>304</x30>
			<y30>237.333333</y30>
			<x31>306</x31>
			<y31>228</y31>
			<x32>298</x32>
			<y32>210.666667</y32>
			<x33>279</x33>
			<y33>204</y33>
			<x34>272</x34>
			<y34>166.666667</y34>
			<x35>267</x35>
			<y35>160</y35>
			<x36>256</x36>
			<y36>70.666667</y36>
			<x37>257</x37>
			<y37>17.333333</y37>
			<x38>254</x38>
			<y38>8</y38>
			<x39>258</x39>
			<y39>0</y39>
			<x40>198</x40>
			<y40>0</y40>
			<x41>197</x41>
			<y41>0</y41>
		</polygon>
	</object>
	<object>
		<name>table</name>
		<pose>Unspecified</pose>
		<truncated>0</truncated>
		<difficult>0</difficult>
		<occluded>0</occluded>
		<bndbox>
			<xmin>154</xmin>
			<xmax>194</xmax>
			<ymin>233</ymin>
			<ymax>373</ymax>
		</bndbox>
		<polygon>
			<x1>171</x1>
			<y1>310.666667</y1>
			<x2>166</x2>
			<y2>341.333333</y2>
			<x3>153</x3>
			<y3>368</y3>
			<x4>181</x4>
			<y4>372</y4>
			<x5>191</x5>
			<y5>368</y5>
			<x6>193</x6>
			<y6>357.333333</y6>
			<x7>180</x7>
			<y7>268</y7>
			<x8>181</x8>
			<y8>236</y8>
			<x9>170</x9>
			<y9>232</y9>
			<x10>164</x10>
			<y10>232</y10>
			<x11>160</x11>
			<y11>233.333333</y11>
			<x12>159</x12>
			<y12>244</y12>
			<x13>168</x13>
			<y13>265.333333</y13>
			<x14>171</x14>
			<y14>310.666667</y14>
		</polygon>
	</object>
	<object>
		<name>person</name>
		<pose>Unspecified</pose>
		<truncated>0</truncated>
		<difficult>0</difficult>
		<occluded>0</occluded>
		<bndbox>
			<xmin>30</xmin>
			<xmax>42</xmax>
			<ymin>294</ymin>
			<ymax>366</ymax>
		</bndbox>
		<polygon>
			<x1>38</x1>
			<y1>365.333333</y1>
			<x2>36</x2>
			<y2>350.666667</y2>
			<x3>41</x3>
			<y3>324</y3>
			<x4>38</x4>
			<y4>293.333333</y4>
			<x5>34</x5>
			<y5>293.333333</y5>
			<x6>29</x6>
			<y6>300</y6>
			<x7>30</x7>
			<y7>338.666667</y7>
			<x8>34</x8>
			<y8>364</y8>
			<x9>38</x9>
			<y9>365.333333</y9>
		</polygon>
	</object>
	<object>
		<name>person</name>
		<pose>Unspecified</pose>
		<truncated>0</truncated>
		<difficult>0</difficult>
		<occluded>0</occluded>
		<bndbox>
			<xmin>6</xmin>
			<xmax>22</xmax>
			<ymin>292</ymin>
			<ymax>381</ymax>
		</bndbox>
		<polygon>
			<x1>14</x1>
			<y1>380</y1>
			<x2>19</x2>
			<y2>373.333333</y2>
			<x3>21</x3>
			<y3>338.666667</y3>
			<x4>21</x4>
			<y4>296</y4>
			<x5>18</x5>
			<y5>290.666667</y5>
			<x6>11</x6>
			<y6>290.666667</y6>
			<x7>5</x7>
			<y7>298.666667</y7>
			<x8>13</x8>
			<y8>353.333333</y8>
			<x9>10</x9>
			<y9>374.666667</y9>
			<x10>14</x10>
			<y10>380</y10>
		</polygon>
	</object>
	<object>
		<name>person</name>
		<pose>Unspecified</pose>
		<truncated>0</truncated>
		<difficult>0</difficult>
		<occluded>0</occluded>
		<bndbox>
			<xmin>1</xmin>
			<xmax>46</xmax>
			<ymin>137</ymin>
			<ymax>270</ymax>
		</bndbox>
		<polygon>
			<x1>2</x1>
			<y1>260</y1>
			<x2>35</x2>
			<y2>262.666667</y2>
			<x3>40</x3>
			<y3>269.333333</y3>
			<x4>39</x4>
			<y4>229.333333</y4>
			<x5>45</x5>
			<y5>218.666667</y5>
			<x6>44</x6>
			<y6>190.666667</y6>
			<x7>36</x7>
			<y7>174.666667</y7>
			<x8>19</x8>
			<y8>165.333333</y8>
			<x9>18</x9>
			<y9>145.333333</y9>
			<x10>10</x10>
			<y10>136</y10>
			<x11>3</x11>
			<y11>136</y11>
			<x12>0</x12>
			<y12>138.666667</y12>
			<x13>3</x13>
			<y13>166.666667</y13>
			<x14>0</x14>
			<y14>173.333333</y14>
			<x15>2</x15>
			<y15>260</y15>
		</polygon>
	</object>
	<object>
		<name>staircase</name>
		<pose>Unspecified</pose>
		<truncated>0</truncated>
		<difficult>0</difficult>
		<occluded>0</occluded>
		<bndbox>
			<xmin>607</xmin>
			<xmax>640</xmax>
			<ymin>181</ymin>
			<ymax>400</ymax>
		</bndbox>
		<polygon>
			<x1>606</x1>
			<y1>220</y1>
			<x2>606</x2>
			<y2>358.666667</y2>
			<x3>610</x3>
			<y3>373.333333</y3>
			<x4>618</x4>
			<y4>374.666667</y4>
			<x5>620</x5>
			<y5>384</y5>
			<x6>631</x6>
			<y6>388</y6>
			<x7>635</x7>
			<y7>398.666667</y7>
			<x8>639</x8>
			<y8>396</y8>
			<x9>639</x9>
			<y9>180</y9>
			<x10>638</x10>
			<y10>180</y10>
			<x11>630</x11>
			<y11>200</y11>
			<x12>625</x12>
			<y12>200</y12>
			<x13>623</x13>
			<y13>206.666667</y13>
			<x14>606</x14>
			<y14>220</y14>
		</polygon>
	</object>
	<object>
		<name>person</name>
		<pose>Unspecified</pose>
		<truncated>0</truncated>
		<difficult>0</difficult>
		<occluded>0</occluded>
		<bndbox>
			<xmin>251</xmin>
			<xmax>264</xmax>
			<ymin>285</ymin>
			<ymax>354</ymax>
		</bndbox>
		<polygon>
			<x1>258</x1>
			<y1>284</y1>
			<x2>256</x2>
			<y2>284</y2>
			<x3>250</x3>
			<y3>317.333333</y3>
			<x4>256</x4>
			<y4>349.333333</y4>
			<x5>263</x5>
			<y5>353.333333</y5>
			<x6>258</x6>
			<y6>284</y6>
		</polygon>
	</object>
	<object>
		<name>person</name>
		<pose>Unspecified</pose>
		<truncated>0</truncated>
		<difficult>0</difficult>
		<occluded>0</occluded>
		<bndbox>
			<xmin>182</xmin>
			<xmax>202</xmax>
			<ymin>241</ymin>
			<ymax>336</ymax>
		</bndbox>
		<polygon>
			<x1>200</x1>
			<y1>285.333333</y1>
			<x2>185</x2>
			<y2>240</y2>
			<x3>182</x3>
			<y3>240</y3>
			<x4>181</x4>
			<y4>265.333333</y4>
			<x5>191</x5>
			<y5>334.666667</y5>
			<x6>201</x6>
			<y6>313.333333</y6>
			<x7>200</x7>
			<y7>285.333333</y7>
		</polygon>
	</object>
	<object>
		<name>person</name>
		<pose>Unspecified</pose>
		<truncated>0</truncated>
		<difficult>0</difficult>
		<occluded>0</occluded>
		<bndbox>
			<xmin>264</xmin>
			<xmax>289</xmax>
			<ymin>241</ymin>
			<ymax>274</ymax>
		</bndbox>
		<polygon>
			<x1>285</x1>
			<y1>273.333333</y1>
			<x2>288</x2>
			<y2>246.666667</y2>
			<x3>269</x3>
			<y3>240</y3>
			<x4>267</x4>
			<y4>240</y4>
			<x5>263</x5>
			<y5>241.333333</y5>
			<x6>268</x6>
			<y6>258.666667</y6>
			<x7>265</x7>
			<y7>273.333333</y7>
			<x8>285</x8>
			<y8>273.333333</y8>
		</polygon>
	</object>
	<object>
		<name>pillar</name>
		<pose>Unspecified</pose>
		<truncated>0</truncated>
		<difficult>0</difficult>
		<occluded>0</occluded>
		<bndbox>
			<xmin>548</xmin>
			<xmax>568</xmax>
			<ymin>298</ymin>
			<ymax>346</ymax>
		</bndbox>
		<polygon>
			<x1>561</x1>
			<y1>297.333333</y1>
			<x2>560</x2>
			<y2>297.333333</y2>
			<x3>547</x3>
			<y3>336</y3>
			<x4>551</x4>
			<y4>345.333333</y4>
			<x5>567</x5>
			<y5>342.666667</y5>
			<x6>561</x6>
			<y6>297.333333</y6>
		</polygon>
	</object>
	<object>
		<name>pillar</name>
		<pose>Unspecified</pose>
		<truncated>0</truncated>
		<difficult>0</difficult>
		<occluded>0</occluded>
		<bndbox>
			<xmin>544</xmin>
			<xmax>570</xmax>
			<ymin>1</ymin>
			<ymax>212</ymax>
		</bndbox>
		<polygon>
			<x1>544</x1>
			<y1>0</y1>
			<x2>543</x2>
			<y2>210.666667</y2>
			<x3>555</x3>
			<y3>204</y3>
			<x4>555</x4>
			<y4>192</y4>
			<x5>560</x5>
			<y5>182.666667</y5>
			<x6>569</x6>
			<y6>182.666667</y6>
			<x7>565</x7>
			<y7>178.666667</y7>
			<x8>567</x8>
			<y8>77.333333</y8>
			<x9>567.2</x9>
			<y9>0</y9>
			<x10>544</x10>
			<y10>0</y10>
		</polygon>
	</object>
</annotation>
